{
    "version": "9.7.8",
    "description": "Collaborative crafting tool for Final Fantasy XIV",
    "homepage": "https://github.com/ffxiv-teamcraft/ffxiv-teamcraft",
    "license": "MIT",
    "autoupdate": {
        "url": "https://github.com/ffxiv-teamcraft/ffxiv-teamcraft/releases/download/v$version/ffxiv-teamcraft-$version-full.nupkg",
        "hash": {
            "url": "$baseurl/RELEASES"
        }
    },
    "checkver": "github",
    "extract_dir": "lib\\net45",
    "hash": "sha1:0140b782845a1e1517cdf9e92a24a30a63d08775",
    "shortcuts": [
        [
            "FFXIV Teamcraft.exe",
            "FFXIV Teamcraft"
        ]
    ],
    "url": "https://github.com/ffxiv-teamcraft/ffxiv-teamcraft/releases/download/v9.7.8/ffxiv-teamcraft-9.7.8-full.nupkg"
}
